ydbf/__init__.py
ydbf/dump.py
ydbf/lib.py
ydbf/reader.py
ydbf/test.py
ydbf/writer.py
ydbf_py3-0.7.post20180112.dist-info/DESCRIPTION.rst
ydbf_py3-0.7.post20180112.dist-info/METADATA
ydbf_py3-0.7.post20180112.dist-info/RECORD
ydbf_py3-0.7.post20180112.dist-info/WHEEL
ydbf_py3-0.7.post20180112.dist-info/entry_points.txt
ydbf_py3-0.7.post20180112.dist-info/metadata.json
ydbf_py3-0.7.post20180112.dist-info/top_level.txt
ydbf_py3-0.7.post20180112.dist-info/zip-safe
