Metadata-Version: 2.0
Name: ydbf-py3
Version: 0.7.post20180112
Summary: Pythonic reader and writer for DBF/XBase files
Home-page: http://www.pyobject.ru/projects/YDbf
Author: Scott Walton
Author-email: s@cott.me.uk
License: GNU GPL2
Platform: UNKNOWN
Classifier: Development Status :: 4 - Beta
Classifier: Intended Audience :: Developers
Classifier: License :: OSI Approved :: GNU General Public License (GPL)
Classifier: Operating System :: OS Independent
Classifier: Programming Language :: Python
Classifier: Programming Language :: Python :: 2.7
Classifier: Programming Language :: Python :: 3.5
Classifier: Topic :: Database
Classifier: Topic :: Software Development :: Libraries :: Python Modules
Requires-Dist: six
